Metadata-Version: 2.1
Name: distrowatchapi
Version: 0.1
Summary: Take a top of distributions from distrowatch.com
Home-page: https://github.com/vovsss/DistrowatchAPI
Author: vovsss
Author-email: vova4ka@internet.ru
License: MIT
License-File: LICENSE
